delver/__init__.py
delver/crawler.py
delver/decorators.py
delver/descriptors.py
delver/exceptions.py
delver/forms.py
delver/helpers.py
delver/logging.json
delver/parser.py
delver/proxies.py
delver/proxies.txt
delver/scraper.py
delver/settings.py
delver/test.py
delver/test_file.txt
delver-0.1.6.dist-info/DESCRIPTION.rst
delver-0.1.6.dist-info/METADATA
delver-0.1.6.dist-info/RECORD
delver-0.1.6.dist-info/WHEEL
delver-0.1.6.dist-info/metadata.json
delver-0.1.6.dist-info/top_level.txt
