Metadata-Version: 2.0
Name: delver
Version: 0.1.6
Summary: Modern user friendly web automation and scraping library.
Home-page: https://github.com/nuncjo/delver
Author: Nuncjo
Author-email: zoreander@gmail.com
License: MIT license
Keywords: delver,web automation,spider,scraper,mechanize,scrapy,robobrowser
Platform: UNKNOWN
Classifier: Development Status :: 2 - Pre-Alpha
Classifier: Intended Audience :: Developers
Classifier: License :: OSI Approved :: MIT License
Classifier: Natural Language :: English
Classifier: Programming Language :: Python :: 3.6
Classifier: Programming Language :: Python :: 3.5
Requires-Dist: cssselect
Requires-Dist: lxml
Requires-Dist: requests
